swahilipro/shell.py
swahilipro/strings_with_arrows.py
swahilipro/swahilipro.py
swahilipro-2.3.0.dist-info/METADATA
swahilipro-2.3.0.dist-info/WHEEL
swahilipro-2.3.0.dist-info/entry_points.txt
swahilipro-2.3.0.dist-info/top_level.txt
swahilipro-2.3.0.dist-info/RECORD
