Metadata-Version: 2.1
Name: swahilipro
Version: 2.3.0
Summary: A compiler package
Author: Masota & Ngigi
Author-email: bonniemasota@gmail.com
